README.txt
setup.py
nbsr/__init__.py
nbsr/exceptions.py
nbsr/nonblocking_reader.py
nbsr/privates.py
nbsr/returnbys.py
nbsr.egg-info/PKG-INFO
nbsr.egg-info/SOURCES.txt
nbsr.egg-info/dependency_links.txt
nbsr.egg-info/not-zip-safe
nbsr.egg-info/top_level.txt