Metadata-Version: 1.2
Name: nbsr
Version: 0.2
Summary: Non-Blocking Stream Reader
Home-page: http://bitbucket.org/netcreator/non-blocking-stream-reader
Author: Karoly
Author-email: karolyjozsa@gmail.com
License: MIT
Platform: UNKNOWN
Classifier: Programming Language :: Python :: 2.7
Classifier: License :: OSI Approved :: MIT License
Classifier: Operating System :: OS Independent
Requires-Python: >=2.7
